src/__init__.py
src/cli.py
src/cmd.py
src/codeMsg.py
src/common.py
src/config.py
src/download.py
src/initTool.py
src/log.py
src/login.py
src/logout.py
src/project.py
src/pull.py
src/push.py
src/run.py
src/upload.py
flowcli-0.0.3.dist-info/METADATA
flowcli-0.0.3.dist-info/WHEEL
flowcli-0.0.3.dist-info/entry_points.txt
flowcli-0.0.3.dist-info/top_level.txt
flowcli-0.0.3.dist-info/RECORD
