Metadata-Version: 2.1
Name: flowcli
Version: 0.0.3
Summary: ft command line tool
Home-page: https://gitee.com/tentech/cli.git
Author: flowcli group
Author-email: flowhub@yeah.net
License: UNKNOWN
Platform: any
Classifier: Programming Language :: Python :: 3
Classifier: License :: OSI Approved :: MIT License
Classifier: Operating System :: OS Independent
Requires-Dist: docker (==4.2.2)
Requires-Dist: fire (==0.3.1)
Requires-Dist: requests (==2.24.0)
Requires-Dist: oss2 (==2.12.1)
